pyfoiltools/__init__.py
pyfoiltools/airfoil.py
pyfoiltools/naca4.py
pyfoiltools/fitting/__init__.py
pyfoiltools/fitting/airfoilbspline.py
pyfoiltools/fitting/airfoilpoly.py
pyfoiltools/fitting/airfoilshape.py
pyfoiltools/fitting/chordspacing.py
pyfoiltools-0.0.1.dist-info/licenses/LICENSE
pyfoiltools-0.0.1.dist-info/METADATA
pyfoiltools-0.0.1.dist-info/WHEEL
pyfoiltools-0.0.1.dist-info/top_level.txt
pyfoiltools-0.0.1.dist-info/RECORD
