Metadata-Version: 2.4
Name: pyfoiltools
Version: 0.0.1
Summary: Python Package containing tools for pyfoil
Author-email: Xero64 <xero64@gmail.com>
License-Expression: MIT
Project-URL: Homepage, https://github.com/Xero64/pyfoiltools
Project-URL: Issues, https://github.com/Xero64/pyfoiltools/issues
Classifier: Programming Language :: Python :: 3
Classifier: Operating System :: OS Independent
Requires-Python: >=3.10
License-File: LICENSE
Requires-Dist: matplotlib>=3.10.5
Requires-Dist: pygeom>=0.0.13
Requires-Dist: numpy>=2.2.6
Requires-Dist: py2md>=0.1.3
Dynamic: license-file
